genai_test_lib/__init__.py
genai_test_lib/generate_qna/__init__.py
genai_test_lib/generate_qna/retrive_qna.py
genai_test_lib/text_comparision/__init__.py
genai_test_lib/text_comparision/output_parser.py
genai_test_lib/text_comparision/text_compare.py
genai_test_lib-1.0.3.dist-info/LICENSE
genai_test_lib-1.0.3.dist-info/METADATA
genai_test_lib-1.0.3.dist-info/WHEEL
genai_test_lib-1.0.3.dist-info/top_level.txt
genai_test_lib-1.0.3.dist-info/RECORD
