Metadata-Version: 2.1
Name: genai-test-lib
Version: 1.0.3
License-File: LICENSE
Requires-Dist: openai
Requires-Dist: langchain
